{"Subjects":{"Subject":[{"id":"s0","image":"images/TF.png","pair":"s7","currentTable":"I"},{"id":"s1","image":"images/BA.png","pair":"s5","currentTable":"D"},{"id":"s2","image":"images/GC.png","currentTable":"C","fixedTable":"C"},{"id":"s3","image":"images/CF.png","currentTable":"G"},{"id":"s4","image":"images/IR.png","pair":"s6","currentTable":"E"},{"id":"s5","image":"images/GA.png","pair":"s1","currentTable":"A"},{"id":"s6","image":"images/JR.png","pair":"s4","currentTable":"F"},{"id":"s7","image":"images/RP.png","pair":"s0","currentTable":"H"},{"id":"s8","image":"images/JG.png","currentTable":"B","fixedTable":"B"},{"id":"s9","image":"images/DF.png","currentTable":"J","fixedTable":"J"},{"id":"s10","image":"images/JS.png","currentTable":"K","fixedTable":"K"},{"id":"s11","image":"images/LM.png","currentTable":"L","fixedTable":"L"}]},"Tables":{"Table":[{"id":"A","image":"images/table.png","pair1":"B","pair2":"D","Position":{"x":"200","y":"100"}},{"id":"B","image":"images/table.png","pair1":"A","pair2":"C","Position":{"x":"300","y":"100"}},{"id":"C","image":"images/table.png","pair1":"B","pair2":"F","Position":{"x":"400","y":"100"}},{"id":"D","image":"images/table.png","pair1":"A","pair2":"","Position":{"x":"200","y":"150"}},{"id":"E","image":"images/table.png","pair1":"F","pair2":"","Position":{"x":"300","y":"150"}},{"id":"F","image":"images/table.png","pair1":"E","pair2":"C","Position":{"x":"400","y":"150"}},{"id":"G","image":"images/table.png","pair1":"H","pair2":"J","Position":{"x":"200","y":"275"}},{"id":"H","image":"images/table.png","pair1":"G","pair2":"I","Position":{"x":"300","y":"250"}},{"id":"I","image":"images/table.png","pair1":"H","pair2":"K","Position":{"x":"400","y":"250"}},{"id":"J","image":"images/table.png","pair1":"K","pair2":"G","Position":{"x":"300","y":"300"}},{"id":"K","image":"images/table.png","pair1":"J","pair2":"I","Position":{"x":"400","y":"300"}},{"id":"L","image":"images/table.png","pair1":"","pair2":"","Position":{"x":"400","y":"400"}}]}}